cfg_load/__init__.py
cfg_load/_version.py
cfg_load/cli.py
cfg_load/paths.py
cfg_load/remote.py
cfg_load-0.9.0.dist-info/LICENSE
cfg_load-0.9.0.dist-info/METADATA
cfg_load-0.9.0.dist-info/WHEEL
cfg_load-0.9.0.dist-info/entry_points.txt
cfg_load-0.9.0.dist-info/top_level.txt
cfg_load-0.9.0.dist-info/RECORD
