Metadata-Version: 2.1
Name: cfg-load
Version: 0.9.0
Summary: Library for loading configuration files
Home-page: https://github.com/MartinThoma/cfg_load
Author: Martin Thoma
Author-email: info@martin-thoma.de
Maintainer: Martin Thoma
Maintainer-email: info@martin-thoma.de
License: MIT
Download-URL: https://github.com/MartinThoma/cfg_load
Keywords: Machine Learning,Data Science
Platform: Linux
Classifier: Development Status :: 3 - Alpha
Classifier: Environment :: Console
Classifier: Intended Audience :: Developers
Classifier: Intended Audience :: Science/Research
Classifier: Intended Audience :: Information Technology
Classifier: License :: OSI Approved :: MIT License
Classifier: Natural Language :: English
Classifier: Programming Language :: Python :: 3.6
Classifier: Programming Language :: Python :: 3.7
Classifier: Programming Language :: Python :: 3.8
Classifier: Topic :: Software Development
Classifier: Topic :: Utilities
Requires-Python: >=3.6
Requires-Dist: mpu[io] (>=0.15.0)
Requires-Dist: pytz (>=2018.4)
Requires-Dist: PyYAML (>=4.2b1)
Requires-Dist: requests (>=2.18.4)
Requires-Dist: six (>=1.11.0)
Provides-Extra: all
Requires-Dist: boto3 ; extra == 'all'
